README.md
setup.cfg
setup.py
polyform/__init__.py
polyform.egg-info/PKG-INFO
polyform.egg-info/SOURCES.txt
polyform.egg-info/dependency_links.txt
polyform.egg-info/top_level.txt