Metadata-Version: 2.1
Name: polyform
Version: 0.2.9
Summary: Serverless DataOps, for AI/ML purposes (Prototype)
Home-page: https://github.com/srevenant/polyform
Author: Brandon Gillespie
Author-email: bjg-pypi@cold.org
License: None
Keywords: dictlib,pyyaml,pylint,pyjwt,boto3,graphql
Platform: UNKNOWN
Classifier: Programming Language :: Python :: 3
Classifier: Operating System :: OS Independent
